easy_symlink/LICENSE
easy_symlink/README.MD
easy_symlink/__init__.py
easy_symlink/requirements.txt
easy_symlink/thirdparty.json
easy_symlink-0.10.dist-info/LICENSE.rst
easy_symlink-0.10.dist-info/METADATA
easy_symlink-0.10.dist-info/WHEEL
easy_symlink-0.10.dist-info/top_level.txt
easy_symlink-0.10.dist-info/RECORD
